{
    "nodes": [
        {
            "timestamp": 1777653877,
            "component": "service|ts-travel-plan-service",
            "state": [
                "degraded",
                "unavailable"
            ]
        },
        {
            "timestamp": 1777653877,
            "component": "span|ts-travel-plan-service::POST /api/v1/travelplanservice/travelPlan/cheapest",
            "state": [
                "missing",
                "healthy",
                "slow"
            ]
        },
        {
            "timestamp": 1777653925,
            "component": "span|ts-ui-dashboard::POST /api/v1/travelplanservice/travelPlan/cheapest",
            "state": [
                "missing",
                "healthy",
                "slow"
            ]
        },
        {
            "timestamp": 1777653877,
            "component": "span|ts-travel-plan-service::TravelPlanController.getByCheapest",
            "state": [
                "missing",
                "healthy",
                "slow"
            ]
        },
        {
            "timestamp": 1777653910,
            "component": "span|ts-travel-plan-service::HttpServletResponseWrapper.sendError",
            "state": [
                "missing"
            ]
        },
        {
            "timestamp": 1777653910,
            "component": "span|ts-travel-plan-service::POST /api/v1/travelplanservice/travelPlan/quickest",
            "state": [
                "missing",
                "healthy",
                "slow"
            ]
        },
        {
            "timestamp": 1777653907,
            "component": "span|ts-ui-dashboard::POST /api/v1/travelplanservice/travelPlan/quickest",
            "state": [
                "missing",
                "healthy",
                "slow"
            ]
        },
        {
            "timestamp": 1777653904,
            "component": "span|ts-travel-plan-service::POST /api/v1/travelplanservice/travelPlan/minStation",
            "state": [
                "missing",
                "healthy",
                "slow"
            ]
        },
        {
            "timestamp": 1777653901,
            "component": "span|ts-ui-dashboard::POST /api/v1/travelplanservice/travelPlan/minStation",
            "state": [
                "missing",
                "healthy",
                "slow"
            ]
        },
        {
            "timestamp": 1777653877,
            "component": "span|ts-travel-plan-service::TravelPlanController.getByQuickest",
            "state": [
                "missing",
                "healthy",
                "slow"
            ]
        },
        {
            "timestamp": 1777653877,
            "component": "span|ts-travel-plan-service::TravelPlanController.getByMinStation",
            "state": [
                "missing",
                "healthy",
                "slow"
            ]
        }
    ],
    "edges": [
        {
            "source": "span|ts-travel-plan-service::TravelPlanController.getByCheapest",
            "target": "span|ts-travel-plan-service::POST /api/v1/travelplanservice/travelPlan/cheapest"
        },
        {
            "source": "service|ts-travel-plan-service",
            "target": "span|ts-travel-plan-service::TravelPlanController.getByMinStation"
        },
        {
            "source": "span|ts-travel-plan-service::TravelPlanController.getByMinStation",
            "target": "span|ts-travel-plan-service::POST /api/v1/travelplanservice/travelPlan/minStation"
        },
        {
            "source": "span|ts-travel-plan-service::POST /api/v1/travelplanservice/travelPlan/minStation",
            "target": "span|ts-ui-dashboard::POST /api/v1/travelplanservice/travelPlan/minStation"
        },
        {
            "source": "service|ts-travel-plan-service",
            "target": "span|ts-travel-plan-service::POST /api/v1/travelplanservice/travelPlan/minStation"
        },
        {
            "source": "span|ts-travel-plan-service::TravelPlanController.getByQuickest",
            "target": "span|ts-travel-plan-service::POST /api/v1/travelplanservice/travelPlan/quickest"
        },
        {
            "source": "span|ts-travel-plan-service::HttpServletResponseWrapper.sendError",
            "target": "span|ts-travel-plan-service::POST /api/v1/travelplanservice/travelPlan/minStation"
        },
        {
            "source": "service|ts-travel-plan-service",
            "target": "span|ts-travel-plan-service::POST /api/v1/travelplanservice/travelPlan/quickest"
        },
        {
            "source": "span|ts-travel-plan-service::POST /api/v1/travelplanservice/travelPlan/cheapest",
            "target": "span|ts-ui-dashboard::POST /api/v1/travelplanservice/travelPlan/cheapest"
        },
        {
            "source": "span|ts-travel-plan-service::POST /api/v1/travelplanservice/travelPlan/quickest",
            "target": "span|ts-ui-dashboard::POST /api/v1/travelplanservice/travelPlan/quickest"
        },
        {
            "source": "span|ts-travel-plan-service::HttpServletResponseWrapper.sendError",
            "target": "span|ts-travel-plan-service::POST /api/v1/travelplanservice/travelPlan/quickest"
        },
        {
            "source": "service|ts-travel-plan-service",
            "target": "span|ts-travel-plan-service::TravelPlanController.getByQuickest"
        },
        {
            "source": "service|ts-travel-plan-service",
            "target": "span|ts-travel-plan-service::HttpServletResponseWrapper.sendError"
        },
        {
            "source": "service|ts-travel-plan-service",
            "target": "span|ts-travel-plan-service::TravelPlanController.getByCheapest"
        },
        {
            "source": "service|ts-travel-plan-service",
            "target": "span|ts-travel-plan-service::POST /api/v1/travelplanservice/travelPlan/cheapest"
        },
        {
            "source": "span|ts-travel-plan-service::HttpServletResponseWrapper.sendError",
            "target": "span|ts-travel-plan-service::POST /api/v1/travelplanservice/travelPlan/cheapest"
        }
    ],
    "root_causes": [
        {
            "timestamp": null,
            "component": "service|ts-travel-plan-service",
            "state": [
                "unknown"
            ]
        }
    ],
    "alarm_nodes": [
        {
            "timestamp": 1777653925,
            "component": "span|ts-ui-dashboard::POST /api/v1/travelplanservice/travelPlan/cheapest",
            "state": [
                "missing",
                "healthy",
                "slow"
            ]
        },
        {
            "timestamp": 1777653910,
            "component": "span|ts-travel-plan-service::POST /api/v1/travelplanservice/travelPlan/quickest",
            "state": [
                "missing",
                "healthy",
                "slow"
            ]
        },
        {
            "timestamp": 1777653907,
            "component": "span|ts-ui-dashboard::POST /api/v1/travelplanservice/travelPlan/quickest",
            "state": [
                "missing",
                "healthy",
                "slow"
            ]
        },
        {
            "timestamp": 1777653904,
            "component": "span|ts-travel-plan-service::POST /api/v1/travelplanservice/travelPlan/minStation",
            "state": [
                "missing",
                "healthy",
                "slow"
            ]
        },
        {
            "timestamp": 1777653901,
            "component": "span|ts-ui-dashboard::POST /api/v1/travelplanservice/travelPlan/minStation",
            "state": [
                "missing",
                "healthy",
                "slow"
            ]
        }
    ],
    "component_to_service": {
        "service|ts-travel-plan-service": "ts-travel-plan-service",
        "span|ts-travel-plan-service::POST /api/v1/travelplanservice/travelPlan/cheapest": "ts-travel-plan-service",
        "span|ts-ui-dashboard::POST /api/v1/travelplanservice/travelPlan/cheapest": "ts-ui-dashboard",
        "span|ts-travel-plan-service::TravelPlanController.getByCheapest": "ts-travel-plan-service",
        "span|ts-travel-plan-service::HttpServletResponseWrapper.sendError": "ts-travel-plan-service",
        "span|ts-travel-plan-service::POST /api/v1/travelplanservice/travelPlan/quickest": "ts-travel-plan-service",
        "span|ts-ui-dashboard::POST /api/v1/travelplanservice/travelPlan/quickest": "ts-ui-dashboard",
        "span|ts-travel-plan-service::POST /api/v1/travelplanservice/travelPlan/minStation": "ts-travel-plan-service",
        "span|ts-ui-dashboard::POST /api/v1/travelplanservice/travelPlan/minStation": "ts-ui-dashboard",
        "span|ts-travel-plan-service::TravelPlanController.getByQuickest": "ts-travel-plan-service",
        "span|ts-travel-plan-service::TravelPlanController.getByMinStation": "ts-travel-plan-service"
    }
}